restdoctor/__init__.py
restdoctor/app_settings.py
restdoctor/apps.py
restdoctor/constants.py
restdoctor/django/__init__.py
restdoctor/django/custom_types.py
restdoctor/django/sensitive_data.py
restdoctor/django/middleware/__init__.py
restdoctor/django/middleware/api_selector.py
restdoctor/management/__init__.py
restdoctor/management/commands/__init__.py
restdoctor/management/commands/generate_schema.py
restdoctor/rest_framework/__init__.py
restdoctor/rest_framework/custom_types.py
restdoctor/rest_framework/exception_handlers.py
restdoctor/rest_framework/exceptions.py
restdoctor/rest_framework/fields.py
restdoctor/rest_framework/generics.py
restdoctor/rest_framework/mixins.py
restdoctor/rest_framework/negotiations.py
restdoctor/rest_framework/parsers.py
restdoctor/rest_framework/renderers.py
restdoctor/rest_framework/resources.py
restdoctor/rest_framework/response.py
restdoctor/rest_framework/reverse.py
restdoctor/rest_framework/routers.py
restdoctor/rest_framework/sensitive_data.py
restdoctor/rest_framework/serializers.py
restdoctor/rest_framework/signals.py
restdoctor/rest_framework/test_client.py
restdoctor/rest_framework/views.py
restdoctor/rest_framework/viewsets.py
restdoctor/rest_framework/pagination/__init__.py
restdoctor/rest_framework/pagination/cursor_uuid.py
restdoctor/rest_framework/pagination/custom_types.py
restdoctor/rest_framework/pagination/mixins.py
restdoctor/rest_framework/pagination/page_number.py
restdoctor/rest_framework/pagination/serializers.py
restdoctor/rest_framework/schema/__init__.py
restdoctor/rest_framework/schema/constants.py
restdoctor/rest_framework/schema/custom_types.py
restdoctor/rest_framework/schema/fields.py
restdoctor/rest_framework/schema/filters.py
restdoctor/rest_framework/schema/generators.py
restdoctor/rest_framework/schema/openapi.py
restdoctor/rest_framework/schema/refs_registry.py
restdoctor/rest_framework/schema/resources.py
restdoctor/rest_framework/schema/serializers.py
restdoctor/rest_framework/schema/utils.py
restdoctor-0.0.64.dist-info/LICENSE
restdoctor-0.0.64.dist-info/METADATA
restdoctor-0.0.64.dist-info/WHEEL
restdoctor-0.0.64.dist-info/top_level.txt
restdoctor-0.0.64.dist-info/RECORD
