Metadata-Version: 2.1
Name: restdoctor
Version: 0.0.64
Summary: BestDoctor's batteries for REST services.
Home-page: UNKNOWN
Author: BestDoctor
Author-email: s.butkin@bestdoctor.ru
License: MIT
Keywords: statistics
Platform: UNKNOWN
Classifier: Environment :: Web Environment
Classifier: Framework :: Django
Classifier: Framework :: Django :: 3.0
Classifier: Framework :: Django :: 3.1
Classifier: Framework :: Django :: 3.2
Classifier: Framework :: Django :: 4.0
Classifier: Framework :: Django :: 4.1
Classifier: Operating System :: OS Independent
Classifier: Topic :: Internet :: WWW/HTTP
Classifier: Programming Language :: Python
Classifier: Programming Language :: Python :: 3.8
Classifier: Programming Language :: Python :: 3.9
Classifier: Programming Language :: Python :: 3.10
Classifier: Programming Language :: Python :: 3.11
License-File: LICENSE
Requires-Dist: semver (==2.13.0)
Requires-Dist: uritemplate (==4.1.1)
